setup.py
scraper_lib/__init__.py
scraper_lib/scraper.py
scraper_lib.egg-info/PKG-INFO
scraper_lib.egg-info/SOURCES.txt
scraper_lib.egg-info/dependency_links.txt
scraper_lib.egg-info/requires.txt
scraper_lib.egg-info/top_level.txt