Metadata-Version: 1.1
Name: scraper-lib
Version: 0.1.0
Summary: Used to make scraping easier
Home-page: https://github.com/xtream1101/scraper-lib
Author: Eddy Hintze
Author-email: eddy.hintze@gmail.com
License: MIT
Platform: UNKNOWN
Classifier: Programming Language :: Python :: 3
Classifier: Development Status :: 4 - Beta
Classifier: Environment :: Other Environment
Classifier: Intended Audience :: Developers
Classifier: Operating System :: OS Independent
Classifier: Topic :: Software Development :: Libraries :: Python Modules
Classifier: Topic :: Utilities
